[
    {
        "productName": "ฟ้าไทย",
        "companyName": "ฟ้าไทย"
    },
    {
        "productName": "คนอร์",
        "companyName": "Unilever"
    },
    {
        "productName": "เวชพงศ์โอสถ",
        "companyName": "เวชพงศ์โอสถ"
    },
    {
        "productName": "นมตรามะลิ",
        "companyName": "นมตรามะลิ"
    },
    {
        "productName": "Izusu",
        "companyName": "Izusu"
    },
    {
        "productName": "Subaru",
        "companyName": "Subaru"
    },
    {
        "productName": "เจเล่บิวตี้",
        "companyName": ""
    },
    {
        "productName": "Oral-B",
        "companyName": ""
    },
    {
        "productName": "Deestone",
        "companyName": ""
    },
    {
        "productName": "คอร์ดี้พลัส",
        "companyName": ""
    },
    {
        "productName": "Dove",
        "companyName": ""
    },
    {
        "productName": "Vaseline",
        "companyName": ""
    },
    {
        "productName": "เทพไทย",
        "companyName": ""
    },
    {
        "productName": "OK Herbal",
        "companyName": ""
    },
    {
        "productName": "Wall's",
        "companyName": ""
    },
    {
        "productName": "Promax",
        "companyName": ""
    },
    {
        "productName": "Citra",
        "companyName": ""
    },
    {
        "productName": "บรีส",
        "companyName": ""
    },
    {
        "productName": "Useful Food",
        "companyName": "Useful Food"
    },
    {
        "productName": "Clear",
        "companyName": ""
    },
    {
        "productName": "air-x",
        "companyName": ""
    },
    {
        "productName": "ไลอ้อน (Lion)",
        "companyName": ""
    },
    {
        "productName": "รอยไทย",
        "companyName": ""
    },
    {
        "productName": "ซาร่า",
        "companyName": ""
    },
    {
        "productName": "อภัยภูเบศร",
        "companyName": ""
    }
]